pharmd/__init__.py
pharmd/all_interactions_last_version.py
pharmd/get_distinct.py
pharmd/get_scores.py
pharmd/md2pharm.py
pharmd/pdb2pharm.py
pharmd/smarts_features.txt
pharmd-0.1.1.dist-info/LICENSE.txt
pharmd-0.1.1.dist-info/METADATA
pharmd-0.1.1.dist-info/WHEEL
pharmd-0.1.1.dist-info/entry_points.txt
pharmd-0.1.1.dist-info/top_level.txt
pharmd-0.1.1.dist-info/RECORD
