Metadata-Version: 2.1
Name: pharmd
Version: 0.1.1
Summary: PharMD: MD pharmacophores and virtual screening
Home-page: https://github.com/ci-lab-cz/pharmd.git
Author: Pavel Polishchuk
Author-email: pavel_polishchuk@ukr.net
License: UNKNOWN
Platform: UNKNOWN
Classifier: Programming Language :: Python :: 3
Classifier: License :: OSI Approved :: BSD License
Classifier: Operating System :: OS Independent
Classifier: Topic :: Scientific/Engineering :: Bio-Informatics
Classifier: Topic :: Scientific/Engineering :: Chemistry
Requires-Python: >=3.6
Requires-Dist: pmapper (>=0.3)
Requires-Dist: psearch (>=0.0.2)
Requires-Dist: plip (>=1.4.2)
Requires-Dist: mdtraj (>=1.9.3)
